{
    "updated":"true",
    "songId":"1",
    "soleMvTitle":"范晓萱最新单曲《放空》",
    "songSrc":"/LiveInYouth/video/mp4/范晓萱 - 放空.mp4",
    "bannerSrc":"/LiveInYouth/images/discoverMusic/soleMv/banner/image_1.jpg",
    "simpleCmts":[
        {
            "userName":"Yuban",
            "content":"只要她还肯露面，只要她还肯唱歌，只要她开心，她怎样都行。",
            "commentId":"1"
        },
        {
            "userName":"Dada",
            "content":"放空 感同身受 有时候觉得融不进大家 觉得好难受 会一瞬间抽离 这是什么病？ 快乐到一半刹住 觉得空洞洞的",
            "commentId":"2"
        },
        {
            "userName":"Allen",
            "content":"属于范晓萱迷幻的味道，像是喝了杯红酒有些微醺，慢慢的放空自己。",
            "commentId":"3"
        }
    ]
}